colocarte_api/__init__.py
colocarte_api/bon_plan.py
colocarte_api/coloc.py
colocarte_api/validation.py
colocarte_api-0.2.1.dist-info/METADATA
colocarte_api-0.2.1.dist-info/WHEEL
colocarte_api-0.2.1.dist-info/top_level.txt
colocarte_api-0.2.1.dist-info/RECORD
